turbodesign/__init__.py
turbodesign/arrayfuncs.py
turbodesign/bladerow.py
turbodesign/cantera_gas/co2.yaml
turbodesign/compressorspool.py
turbodesign/coolant.py
turbodesign/enums.py
turbodesign/inlet.py
turbodesign/isentropic.py
turbodesign/loss/__init__.py
turbodesign/loss/compressor/__init__.py
turbodesign/loss/losstype.py
turbodesign/loss/turbine/TD2.py
turbodesign/loss/turbine/__init__.py
turbodesign/loss/turbine/ainleymathieson.py
turbodesign/loss/turbine/craigcox.py
turbodesign/loss/turbine/fixedefficiency.py
turbodesign/loss/turbine/fixedpressureloss.py
turbodesign/loss/turbine/kackerokapuu.py
turbodesign/loss/turbine/traupel.py
turbodesign/lossinterp.py
turbodesign/outlet.py
turbodesign/passage.py
turbodesign/radeq.py
turbodesign/rotor.py
turbodesign/solve_radeq.py
turbodesign/spool.py
turbodesign/stage.py
turbodesign/td_math.py
turbodesign/turbinespool.py
turbo_design-1.3.6.dist-info/METADATA
turbo_design-1.3.6.dist-info/WHEEL
turbo_design-1.3.6.dist-info/RECORD
