Metadata-Version: 2.3
Name: turbo-design
Version: 1.3.6
Summary: TurboDesign is a library used to design turbines and compressors using radial equilibrium.
Author: Paht Juangphanich
Author-email: paht.juangphanich@nasa.gov
Requires-Python: >=3.9
Classifier: Programming Language :: Python :: 3
Classifier: Programming Language :: Python :: 3.9
Classifier: Programming Language :: Python :: 3.10
Classifier: Programming Language :: Python :: 3.11
Classifier: Programming Language :: Python :: 3.12
Classifier: Programming Language :: Python :: 3.13
Requires-Dist: cantera
Requires-Dist: findiff
Requires-Dist: matplotlib
Requires-Dist: numpy
Requires-Dist: pandas
Requires-Dist: plot3d
Requires-Dist: pyturbo-aero
Requires-Dist: scipy
